nlp_chains/__init__.py
nlp_chains/agents/__init__.py
nlp_chains/agents.py
nlp_chains/chains/__init__.py
nlp_chains/chains/nlu_annotator.py
nlp_chains/chains.py
nlp_chains-0.1.0.dist-info/METADATA
nlp_chains-0.1.0.dist-info/WHEEL
nlp_chains-0.1.0.dist-info/RECORD
